jaen_mod/__init__.py
jaen_mod/jaen.py
jaen_mod/test.py
jaen_mod-0.0.7.dist-info/METADATA
jaen_mod-0.0.7.dist-info/WHEEL
jaen_mod-0.0.7.dist-info/top_level.txt
jaen_mod-0.0.7.dist-info/RECORD
